zvault/__init__.py
zvault/cli.py
zvault/crypto.py
zvault-0.1.9.dist-info/METADATA
zvault-0.1.9.dist-info/WHEEL
zvault-0.1.9.dist-info/entry_points.txt
zvault-0.1.9.dist-info/top_level.txt
zvault-0.1.9.dist-info/RECORD
