Metadata-Version: 2.4
Name: zvault
Version: 0.1.9
Summary: Terminal password + key manager using AES encryption
Author-email: Zero <your-email@example.com>
Requires-Python: >=3.8
Requires-Dist: cryptography
Requires-Dist: pyperclip
Requires-Dist: rich
Requires-Dist: pyotp
